test_common/__init__.py
test_common/_random/__init__.py
test_common/_random/strings.py
test_common/benchmark/__init__.py
test_common/benchmark/timing.py
test_common/fs/__init__.py
test_common/fs/crypto.py
test_common/fs/ops.py
test_common/fs/temp.py
test_common/system/__init__.py
test_common/system/env.py
test_common/system/output.py
test_common/tests/__init__.py
test_common/tests/test_crypto.py
test_common/tests/test_ops.py
test_common/tests/test_random_strings.py
test_common/tests/test_system_env.py
test_common/tests/test_system_output.py
test_common/tests/test_temp.py
test_common/tests/test_timing.py
test_common-1.3.0.post3.dist-info/LICENSE
test_common-1.3.0.post3.dist-info/METADATA
test_common-1.3.0.post3.dist-info/WHEEL
test_common-1.3.0.post3.dist-info/top_level.txt
test_common-1.3.0.post3.dist-info/RECORD
