Metadata-Version: 2.1
Name: test_common
Version: 1.3.0.post3
Summary: Common functions useful for tests.
Home-page: https://github.com/dante-signal31/test_common_python
Author: Dante Signal31
Author-email: dante.signal31@gmail.com
License: BSD-3
Download-URL: https://pypi.org/project/test-common/
Keywords: test
Platform: UNKNOWN
Classifier: Development Status :: 4 - Beta
Classifier: Intended Audience :: Developers
Classifier: Intended Audience :: Other Audience
Classifier: Topic :: System
Classifier: License :: OSI Approved :: BSD License
Classifier: Operating System :: POSIX :: Linux
Classifier: Programming Language :: Python :: 3
Classifier: Programming Language :: Python :: 3.7
License-File: LICENSE
